[
  {
    "name": "Advisory committee members (appointed experts)",
    "types": [
      "office"
    ],
    "topics": [
      "061"
    ]
  },
  {
    "name": "Agency budget and program officials",
    "types": [
      "office"
    ],
    "topics": [
      "034"
    ]
  },
  {
    "name": "Agency budget officers",
    "types": [
      "office"
    ],
    "topics": [
      "058"
    ]
  },
  {
    "name": "Agency chief financial officers",
    "types": [
      "office"
    ],
    "topics": [
      "047",
      "057"
    ]
  },
  {
    "name": "Agency general counsels",
    "types": [
      "office"
    ],
    "topics": [
      "060"
    ]
  },
  {
    "name": "Agency rulemaking and legal offices",
    "types": [
      "office"
    ],
    "topics": [
      "049"
    ]
  },
  {
    "name": "Agency rulemaking offices",
    "types": [
      "office"
    ],
    "topics": [
      "044",
      "059",
      "064"
    ]
  },
  {
    "name": "Cabinet secretaries and agency heads",
    "types": [
      "office"
    ],
    "topics": [
      "054"
    ]
  },
  {
    "name": "Campaigns and party committees",
    "types": [
      "political_entity"
    ],
    "topics": [
      "015"
    ]
  },
  {
    "name": "Candidate committees and party committees",
    "types": [
      "political_entity"
    ],
    "topics": [
      "009",
      "013"
    ]
  },
  {
    "name": "Candidates and campaigns",
    "types": [
      "political_entity"
    ],
    "topics": [
      "001"
    ]
  },
  {
    "name": "Career Senior Executive Service members",
    "types": [
      "office"
    ],
    "topics": [
      "046"
    ]
  },
  {
    "name": "Commission chairs and members",
    "types": [
      "office"
    ],
    "topics": [
      "062"
    ]
  },
  {
    "name": "Commission staff and investigators",
    "types": [
      "office"
    ],
    "topics": [
      "062"
    ]
  },
  {
    "name": "Committee chairs (House and Senate)",
    "types": [
      "political_entity"
    ],
    "topics": [
      "018"
    ]
  },
  {
    "name": "Committee staff",
    "types": [
      "office"
    ],
    "topics": [
      "031",
      "033",
      "036",
      "039"
    ]
  },
  {
    "name": "Congressional appropriations committees",
    "types": [
      "political_entity"
    ],
    "topics": [
      "047"
    ]
  },
  {
    "name": "Congressional budget and appropriations leadership",
    "types": [
      "office"
    ],
    "topics": [
      "025"
    ]
  },
  {
    "name": "Congressional Budget Office",
    "types": [
      "office"
    ],
    "topics": [
      "025",
      "026",
      "039"
    ]
  },
  {
    "name": "Congressional campaign committees",
    "types": [
      "political_entity"
    ],
    "topics": [
      "019"
    ]
  },
  {
    "name": "Congressional caucus members",
    "types": [
      "political_entity"
    ],
    "topics": [
      "028"
    ]
  },
  {
    "name": "Congressional leadership",
    "types": [
      "political_entity"
    ],
    "topics": [
      "018",
      "021",
      "028",
      "033",
      "042"
    ]
  },
  {
    "name": "Congressional leadership and fiscal negotiating blocs",
    "types": [
      "office"
    ],
    "topics": [
      "026"
    ]
  },
  {
    "name": "Congressional oversight committees",
    "types": [
      "committee",
      "political_entity"
    ],
    "topics": [
      "032",
      "045",
      "051"
    ]
  },
  {
    "name": "Congressional Research Service",
    "types": [
      "office"
    ],
    "topics": [
      "035"
    ]
  },
  {
    "name": "Connected PACs (corporate, union, trade-association affiliated)",
    "types": [
      "institution"
    ],
    "topics": [
      "017"
    ]
  },
  {
    "name": "Consultants, media vendors, and former campaign staff",
    "types": [
      "political_entity"
    ],
    "topics": [
      "013"
    ]
  },
  {
    "name": "Consulting firms (media, polling, digital, mail, field)",
    "types": [
      "institution"
    ],
    "topics": [
      "009"
    ]
  },
  {
    "name": "Convention delegates",
    "types": [
      "institution"
    ],
    "topics": [
      "011"
    ]
  },
  {
    "name": "Council of the Inspectors General on Integrity and Efficiency",
    "types": [
      "office"
    ],
    "topics": [
      "045"
    ]
  },
  {
    "name": "County and local party units",
    "types": [
      "political_entity"
    ],
    "topics": [
      "014"
    ]
  },
  {
    "name": "County election officials",
    "types": [
      "institution"
    ],
    "topics": [
      "008"
    ]
  },
  {
    "name": "County/local election administrators",
    "types": [
      "institution"
    ],
    "topics": [
      "016"
    ]
  },
  {
    "name": "Courts (state trial/appellate, federal district/circuit, Supreme Court)",
    "types": [
      "court"
    ],
    "topics": [
      "015"
    ]
  },
  {
    "name": "Data and software vendors",
    "types": [
      "institution"
    ],
    "topics": [
      "009"
    ]
  },
  {
    "name": "Data brokers and analytics vendors",
    "types": [
      "institution"
    ],
    "topics": [
      "010"
    ]
  },
  {
    "name": "Defense Counterintelligence and Security Agency",
    "types": [
      "office"
    ],
    "topics": [
      "053"
    ]
  },
  {
    "name": "Designated Federal Officers",
    "types": [
      "office"
    ],
    "topics": [
      "061"
    ]
  },
  {
    "name": "Election administrators",
    "types": [
      "institution"
    ],
    "topics": [
      "006"
    ]
  },
  {
    "name": "Election Assistance Commission (EAC)",
    "types": [
      "regulatory_body"
    ],
    "topics": [
      "004"
    ]
  },
  {
    "name": "Electors",
    "types": [
      "institution"
    ],
    "topics": [
      "007"
    ]
  },
  {
    "name": "Executive Office of the President senior staff",
    "types": [
      "office"
    ],
    "topics": [
      "043"
    ]
  },
  {
    "name": "Federal agencies under audit",
    "types": [
      "institution"
    ],
    "topics": [
      "032"
    ]
  },
  {
    "name": "Federal agency rulemaking offices",
    "types": [
      "office"
    ],
    "topics": [
      "048"
    ]
  },
  {
    "name": "Federal courts (judicial review)",
    "types": [
      "office"
    ],
    "topics": [
      "048"
    ]
  },
  {
    "name": "Federal Election Commission",
    "types": [
      "regulatory_body"
    ],
    "topics": [
      "027"
    ]
  },
  {
    "name": "Floor leadership and managers",
    "types": [
      "political_entity"
    ],
    "topics": [
      "037",
      "038"
    ]
  },
  {
    "name": "Full appropriations committee leadership",
    "types": [
      "office"
    ],
    "topics": [
      "034"
    ]
  },
  {
    "name": "Government Accountability Office",
    "types": [
      "regulatory_body"
    ],
    "topics": [
      "018",
      "032"
    ]
  },
  {
    "name": "Government Accountability Office (compliance audit)",
    "types": [
      "office"
    ],
    "topics": [
      "057"
    ]
  },
  {
    "name": "Government Accountability Office (FVRA monitoring)",
    "types": [
      "office"
    ],
    "topics": [
      "050",
      "065"
    ]
  },
  {
    "name": "Government Publishing Office",
    "types": [
      "office"
    ],
    "topics": [
      "049"
    ]
  },
  {
    "name": "Governors",
    "types": [
      "institution"
    ],
    "topics": [
      "003"
    ]
  },
  {
    "name": "GSA Committee Management Secretariat",
    "types": [
      "office"
    ],
    "topics": [
      "061"
    ]
  },
  {
    "name": "House and Senate Appropriations Committees",
    "types": [
      "committee"
    ],
    "topics": [
      "021"
    ]
  },
  {
    "name": "House and Senate appropriations subcommittees",
    "types": [
      "committee"
    ],
    "topics": [
      "034"
    ]
  },
  {
    "name": "House and Senate conferees",
    "types": [
      "political_entity"
    ],
    "topics": [
      "033"
    ]
  },
  {
    "name": "House and Senate Offices of Legislative Counsel",
    "types": [
      "office"
    ],
    "topics": [
      "031"
    ]
  },
  {
    "name": "House committee chairs and bill sponsors",
    "types": [
      "political_entity"
    ],
    "topics": [
      "023"
    ]
  },
  {
    "name": "House Committee on Ethics",
    "types": [
      "committee"
    ],
    "topics": [
      "029"
    ]
  },
  {
    "name": "House leadership and Rules Committee",
    "types": [
      "office"
    ],
    "topics": [
      "030"
    ]
  },
  {
    "name": "House Office of Legislative Counsel",
    "types": [
      "office"
    ],
    "topics": [
      "036"
    ]
  },
  {
    "name": "House party leadership",
    "types": [
      "political_entity"
    ],
    "topics": [
      "022",
      "023",
      "040"
    ]
  },
  {
    "name": "House Rules Committee",
    "types": [
      "committee",
      "political_entity"
    ],
    "topics": [
      "020",
      "040"
    ]
  },
  {
    "name": "Incumbent officeholders",
    "types": [
      "institution"
    ],
    "topics": [
      "002"
    ]
  },
  {
    "name": "Independent and bipartisan redistricting commissions",
    "types": [
      "regulatory_body"
    ],
    "topics": [
      "003"
    ]
  },
  {
    "name": "Independent expenditure-only committees (super PACs)",
    "types": [
      "political_entity"
    ],
    "topics": [
      "013"
    ]
  },
  {
    "name": "Individual U.S. Senators",
    "types": [
      "political_entity"
    ],
    "topics": [
      "024",
      "041"
    ]
  },
  {
    "name": "Initiative sponsors",
    "types": [
      "institution"
    ],
    "topics": [
      "005"
    ]
  },
  {
    "name": "Inspectors General (presidentially appointed)",
    "types": [
      "office"
    ],
    "topics": [
      "045"
    ]
  },
  {
    "name": "Leadership PACs",
    "types": [
      "institution"
    ],
    "topics": [
      "017"
    ]
  },
  {
    "name": "Legislative staff users of CRS analysis",
    "types": [
      "office"
    ],
    "topics": [
      "035"
    ]
  },
  {
    "name": "Members of Congress",
    "types": [
      "political_entity"
    ],
    "topics": [
      "031",
      "035",
      "037",
      "038"
    ]
  },
  {
    "name": "Members of Congress and candidates",
    "types": [
      "political_entity"
    ],
    "topics": [
      "027"
    ]
  },
  {
    "name": "Members of the U.S. House of Representatives",
    "types": [
      "political_entity"
    ],
    "topics": [
      "022"
    ]
  },
  {
    "name": "Merit Systems Protection Board",
    "types": [
      "office"
    ],
    "topics": [
      "046"
    ]
  },
  {
    "name": "Minority committee staff",
    "types": [
      "office"
    ],
    "topics": [
      "039"
    ]
  },
  {
    "name": "National party committees (DNC/RNC and congressional campaign committees)",
    "types": [
      "political_entity"
    ],
    "topics": [
      "014"
    ]
  },
  {
    "name": "National party committees (DNC/RNC)",
    "types": [
      "political_entity"
    ],
    "topics": [
      "011",
      "012"
    ]
  },
  {
    "name": "National Security Advisor",
    "types": [
      "office"
    ],
    "topics": [
      "054"
    ]
  },
  {
    "name": "National Security Council staff",
    "types": [
      "office"
    ],
    "topics": [
      "043"
    ]
  },
  {
    "name": "Nonconnected PACs",
    "types": [
      "institution"
    ],
    "topics": [
      "017"
    ]
  },
  {
    "name": "NSC staff (coordination function)",
    "types": [
      "office"
    ],
    "topics": [
      "054"
    ]
  },
  {
    "name": "Office of Congressional Ethics",
    "types": [
      "office"
    ],
    "topics": [
      "029"
    ]
  },
  {
    "name": "Office of Information and Regulatory Affairs",
    "types": [
      "office"
    ],
    "topics": [
      "044",
      "048"
    ]
  },
  {
    "name": "Office of Legal Counsel",
    "types": [
      "office"
    ],
    "topics": [
      "052"
    ]
  },
  {
    "name": "Office of Legal Counsel (OLC)",
    "types": [
      "office"
    ],
    "topics": [
      "060"
    ]
  },
  {
    "name": "Office of Management and Budget",
    "types": [
      "office"
    ],
    "topics": [
      "021",
      "025",
      "047"
    ]
  },
  {
    "name": "Office of Management and Budget (circular authority)",
    "types": [
      "office"
    ],
    "topics": [
      "057"
    ]
  },
  {
    "name": "Office of Personnel Management",
    "types": [
      "office"
    ],
    "topics": [
      "046"
    ]
  },
  {
    "name": "Office of the Clerk, U.S. House of Representatives",
    "types": [
      "office"
    ],
    "topics": [
      "022",
      "023"
    ]
  },
  {
    "name": "Office of the Director of National Intelligence",
    "types": [
      "office"
    ],
    "topics": [
      "053"
    ]
  },
  {
    "name": "Office of the Federal Register",
    "types": [
      "office"
    ],
    "topics": [
      "049",
      "055"
    ]
  },
  {
    "name": "Office of the Pardon Attorney (DOJ)",
    "types": [
      "office"
    ],
    "topics": [
      "056"
    ]
  },
  {
    "name": "OIRA (significant rule review)",
    "types": [
      "office"
    ],
    "topics": [
      "064"
    ]
  },
  {
    "name": "OIRA Administrator",
    "types": [
      "office"
    ],
    "topics": [
      "059"
    ]
  },
  {
    "name": "OMB Director and resource management offices",
    "types": [
      "office"
    ],
    "topics": [
      "058"
    ]
  },
  {
    "name": "Parliamentarian offices",
    "types": [
      "office"
    ],
    "topics": [
      "030",
      "037",
      "038",
      "040",
      "041"
    ]
  },
  {
    "name": "Participating agency representatives",
    "types": [
      "office"
    ],
    "topics": [
      "063"
    ]
  },
  {
    "name": "Party campaign committees",
    "types": [
      "political_entity"
    ],
    "topics": [
      "027"
    ]
  },
  {
    "name": "Platform committee members and subcommittee chairs",
    "types": [
      "political_entity"
    ],
    "topics": [
      "011"
    ]
  },
  {
    "name": "Political Action Committees (PACs)",
    "types": [
      "political_entity"
    ],
    "topics": [
      "001"
    ]
  },
  {
    "name": "Political campaigns and party committees",
    "types": [
      "political_entity"
    ],
    "topics": [
      "010"
    ]
  },
  {
    "name": "Political party committees",
    "types": [
      "political_entity"
    ],
    "topics": [
      "001"
    ]
  },
  {
    "name": "President (appointment authority)",
    "types": [
      "office"
    ],
    "topics": [
      "050"
    ]
  },
  {
    "name": "President (Article II pardon authority)",
    "types": [
      "office"
    ],
    "topics": [
      "056"
    ]
  },
  {
    "name": "President (classification authority)",
    "types": [
      "office"
    ],
    "topics": [
      "053"
    ]
  },
  {
    "name": "President (designation authority)",
    "types": [
      "office"
    ],
    "topics": [
      "065"
    ]
  },
  {
    "name": "President (directive authority)",
    "types": [
      "office"
    ],
    "topics": [
      "044",
      "055"
    ]
  },
  {
    "name": "President (emergency declaration authority)",
    "types": [
      "office"
    ],
    "topics": [
      "051"
    ]
  },
  {
    "name": "President (privilege invocation authority)",
    "types": [
      "office"
    ],
    "topics": [
      "052"
    ]
  },
  {
    "name": "President (signing statement authority)",
    "types": [
      "office"
    ],
    "topics": [
      "060"
    ]
  },
  {
    "name": "President and congressional leadership (commission creation)",
    "types": [
      "political_entity"
    ],
    "topics": [
      "062"
    ]
  },
  {
    "name": "Presidential campaigns",
    "types": [
      "political_entity"
    ],
    "topics": [
      "007",
      "012"
    ]
  },
  {
    "name": "Professional signature-gathering firms",
    "types": [
      "institution"
    ],
    "topics": [
      "005"
    ]
  },
  {
    "name": "Public commenters (industry, advocacy, citizens)",
    "types": [
      "political_entity"
    ],
    "topics": [
      "064"
    ]
  },
  {
    "name": "Rank-and-file members in swing blocs",
    "types": [
      "political_entity"
    ],
    "topics": [
      "042"
    ]
  },
  {
    "name": "Senate (advise-and-consent authority)",
    "types": [
      "political_entity"
    ],
    "topics": [
      "050",
      "065"
    ]
  },
  {
    "name": "Senate leadership and individual senators",
    "types": [
      "political_entity"
    ],
    "topics": [
      "030"
    ]
  },
  {
    "name": "Senate Majority and Minority Leaders",
    "types": [
      "political_entity"
    ],
    "topics": [
      "019"
    ]
  },
  {
    "name": "Senate Office of the Legislative Counsel",
    "types": [
      "office"
    ],
    "topics": [
      "036"
    ]
  },
  {
    "name": "Senate Parliamentarian",
    "types": [
      "office",
      "political_entity"
    ],
    "topics": [
      "020",
      "024"
    ]
  },
  {
    "name": "Senate party leadership",
    "types": [
      "political_entity"
    ],
    "topics": [
      "020",
      "024",
      "041"
    ]
  },
  {
    "name": "Senate Select Committee on Ethics",
    "types": [
      "committee"
    ],
    "topics": [
      "029"
    ]
  },
  {
    "name": "Speaker of the House",
    "types": [
      "political_entity"
    ],
    "topics": [
      "019"
    ]
  },
  {
    "name": "State and local election officials",
    "types": [
      "institution"
    ],
    "topics": [
      "004"
    ]
  },
  {
    "name": "State and local governments",
    "types": [
      "institution"
    ],
    "topics": [
      "006"
    ]
  },
  {
    "name": "State and national party committees",
    "types": [
      "political_entity"
    ],
    "topics": [
      "002"
    ]
  },
  {
    "name": "State canvassing authority / Secretary of State",
    "types": [
      "regulatory_body"
    ],
    "topics": [
      "008"
    ]
  },
  {
    "name": "State election administrators",
    "types": [
      "institution"
    ],
    "topics": [
      "010"
    ]
  },
  {
    "name": "State election officials and attorneys general",
    "types": [
      "institution"
    ],
    "topics": [
      "015"
    ]
  },
  {
    "name": "State election officials and canvassing boards",
    "types": [
      "institution"
    ],
    "topics": [
      "016"
    ]
  },
  {
    "name": "State governments",
    "types": [
      "institution"
    ],
    "topics": [
      "002"
    ]
  },
  {
    "name": "State legislature",
    "types": [
      "institution"
    ],
    "topics": [
      "005",
      "008"
    ]
  },
  {
    "name": "State legislatures",
    "types": [
      "institution"
    ],
    "topics": [
      "003",
      "004",
      "007",
      "016"
    ]
  },
  {
    "name": "State party committees",
    "types": [
      "political_entity"
    ],
    "topics": [
      "014"
    ]
  },
  {
    "name": "State party organizations",
    "types": [
      "political_entity"
    ],
    "topics": [
      "012"
    ]
  },
  {
    "name": "Task force chairs (senior White House or agency officials)",
    "types": [
      "office"
    ],
    "topics": [
      "063"
    ]
  },
  {
    "name": "U.S. Department of the Treasury",
    "types": [
      "office"
    ],
    "topics": [
      "026"
    ]
  },
  {
    "name": "Voting equipment vendors and state certification authorities",
    "types": [
      "institution"
    ],
    "topics": [
      "006"
    ]
  },
  {
    "name": "Whip organizations",
    "types": [
      "office"
    ],
    "topics": [
      "028",
      "042"
    ]
  },
  {
    "name": "White House Chief of Staff",
    "types": [
      "office"
    ],
    "topics": [
      "043"
    ]
  },
  {
    "name": "White House counsel",
    "types": [
      "office"
    ],
    "topics": [
      "052",
      "055",
      "056"
    ]
  },
  {
    "name": "White House counsel and NSC staff",
    "types": [
      "office"
    ],
    "topics": [
      "051"
    ]
  },
  {
    "name": "White House policy councils (DPC, NEC, OSTP)",
    "types": [
      "office"
    ],
    "topics": [
      "059"
    ]
  },
  {
    "name": "White House policy councils (NEC, DPC)",
    "types": [
      "office"
    ],
    "topics": [
      "058"
    ]
  },
  {
    "name": "White House policy councils (NSC, DPC)",
    "types": [
      "office"
    ],
    "topics": [
      "063"
    ]
  }
]
